pytorch_lightning_spells/__init__.py
pytorch_lightning_spells/callbacks.py
pytorch_lightning_spells/cutmix_utils.py
pytorch_lightning_spells/loggers.py
pytorch_lightning_spells/losses.py
pytorch_lightning_spells/lr_schedulers.py
pytorch_lightning_spells/metrics.py
pytorch_lightning_spells/optimizers.py
pytorch_lightning_spells/samplers.py
pytorch_lightning_spells/snapmix_utils.py
pytorch_lightning_spells/utils.py
pytorch_lightning_spells/version.py
pytorch_lightning_spells/tests/test_callbacks.py
pytorch_lightning_spells/tests/test_optimizers.py
pytorch_lightning_spells-0.2.1.dist-info/METADATA
pytorch_lightning_spells-0.2.1.dist-info/WHEEL
pytorch_lightning_spells-0.2.1.dist-info/licenses/LICENSE
pytorch_lightning_spells-0.2.1.dist-info/RECORD
