Metadata-Version: 2.4
Name: pytorch-lightning-spells
Version: 0.2.1
Summary: Some useful plugins for PyTorch Lightning.
License-File: LICENSE
Requires-Python: >=3.11
Requires-Dist: pytorch-lightning<2.6.0,>=2.5.0
Requires-Dist: scikit-learn>=1.7.1
Requires-Dist: scipy>=1.16.1
Requires-Dist: typing-extensions>=4.15.0
Provides-Extra: telegram
Requires-Dist: python-telegram-bot>=22.3; extra == 'telegram'
